fastapi_viewsets/__init__.py
fastapi_viewsets/constants.py
fastapi_viewsets/db_conf.py
fastapi_viewsets/utils.py
fastapi_viewsets-0.1.5.dist-info/LICENSE
fastapi_viewsets-0.1.5.dist-info/METADATA
fastapi_viewsets-0.1.5.dist-info/WHEEL
fastapi_viewsets-0.1.5.dist-info/top_level.txt
fastapi_viewsets-0.1.5.dist-info/RECORD
