Metadata-Version: 2.1
Name: fastapi-viewsets
Version: 0.1.5
Summary: Package for creating endpoint
Home-page: https://github.com/svalench/fastapi_viewsets
Author: Alexander Valenchits
License: UNKNOWN
Platform: UNKNOWN
Classifier: Programming Language :: Python :: 3.9
Classifier: License :: OSI Approved :: MIT License
Classifier: Operating System :: OS Independent
Requires-Python: >=3.6
License-File: LICENSE
Requires-Dist: fastapi (>=0.76.0)
Requires-Dist: uvicorn (>=0.17.6)
Requires-Dist: SQLAlchemy (>=1.4.36)
